MANIFEST.in
setup.cfg
setup.py
docs/Header.png
docs/README.md
docs/image.png
docs/uvicmuse_.png
uvicmuse/Backend.py
uvicmuse/__init__.py
uvicmuse/__main__.py
uvicmuse/constants.py
uvicmuse/helper.py
uvicmuse/interface.py
uvicmuse/muse.py
uvicmuse/docs/Header.png
uvicmuse_dongle.egg-info/PKG-INFO
uvicmuse_dongle.egg-info/SOURCES.txt
uvicmuse_dongle.egg-info/dependency_links.txt
uvicmuse_dongle.egg-info/entry_points.txt
uvicmuse_dongle.egg-info/not-zip-safe
uvicmuse_dongle.egg-info/requires.txt
uvicmuse_dongle.egg-info/top_level.txt