Metadata-Version: 2.1
Name: uvicmuse-dongle
Version: 1.0.0
Summary: Stream and visualize EEG data from the Muse headset.
Home-page: UNKNOWN
Author: Bardia Barabadi
Author-email: bardiabarabadi@uvic.ca
License: MIT
Keywords: muse lsl eeg ble neuroscience matlab UDP
Platform: UNKNOWN
Classifier: Development Status :: 4 - Beta
Classifier: Intended Audience :: Science/Research
Classifier: Topic :: Software Development
Classifier: Operating System :: Microsoft :: Windows
Classifier: Operating System :: POSIX
Classifier: Operating System :: Unix
Classifier: Operating System :: MacOS
Classifier: Programming Language :: Python
